.travis.yml
AUTHORS
ChangeLog
LICENSE
README.rst
requirements.txt
setup.cfg
setup.py
tox.ini
pytest_easyMPI/__init__.py
pytest_easyMPI/_decorator.py
pytest_easyMPI/_mpi_test_parser.py
pytest_easyMPI/_plugin.py
pytest_easyMPI/_print_capture.py
pytest_easyMPI.egg-info/PKG-INFO
pytest_easyMPI.egg-info/SOURCES.txt
pytest_easyMPI.egg-info/dependency_links.txt
pytest_easyMPI.egg-info/entry_points.txt
pytest_easyMPI.egg-info/not-zip-safe
pytest_easyMPI.egg-info/pbr.json
pytest_easyMPI.egg-info/requires.txt
pytest_easyMPI.egg-info/top_level.txt
tests/__init__.py
tests/test_decorator.py