Metadata-Version: 1.1
Name: pytest-easyMPI
Version: 0.0.1
Summary: Package that supports mpi tests in pytest
Home-page: https://github.com/NOhs/pytest-easyMPI
Author: NOhs
Author-email: UNKNOWN
License: MIT
Keywords: mpi, pytest
Platform: UNKNOWN
Classifier: Programming Language :: Python
Classifier: Framework :: Pytest
